[{"Name":"C++ Header","Bytes":30685464,"CodeBytes":0,"Lines":896967,"Code":701619,"Comment":75102,"Blank":120246,"Complexity":39717,"Count":5478,"WeightedComplexity":0,"Files":[],"LineLength":null,"ULOC":0},{"Name":"C Header","Bytes":19038108,"CodeBytes":0,"Lines":573150,"Code":197376,"Comment":304305,"Blank":71469,"Complexity":15660,"Count":933,"WeightedComplexity":0,"Files":[],"LineLength":null,"ULOC":0},{"Name":"C++","Bytes":15470403,"CodeBytes":0,"Lines":503511,"Code":324438,"Comment":84792,"Blank":94281,"Complexity":42771,"Count":723,"WeightedComplexity":0,"Files":[],"LineLength":null,"ULOC":0},{"Name":"Autoconf","Bytes":253071,"CodeBytes":0,"Lines":7392,"Code":5670,"Comment":492,"Blank":1230,"Complexity":597,"Count":54,"WeightedComplexity":0,"Files":[],"LineLength":null,"ULOC":0},{"Name":"Makefile","Bytes":669,"CodeBytes":0,"Lines":21,"Code":15,"Comment":3,"Blank":3,"Complexity":0,"Count":3,"WeightedComplexity":0,"Files":[],"LineLength":null,"ULOC":0},{"Name":"Batch","Bytes":9816,"CodeBytes":0,"Lines":148,"Code":148,"Comment":0,"Blank":0,"Complexity":0,"Count":2,"WeightedComplexity":0,"Files":[],"LineLength":null,"ULOC":0},{"Name":"HTML","Bytes":2039166,"CodeBytes":0,"Lines":55362,"Code":50932,"Comment":1153,"Blank":3277,"Complexity":0,"Count":2,"WeightedComplexity":0,"Files":[],"LineLength":null,"ULOC":0},{"Name":"Plain Text","Bytes":13431,"CodeBytes":0,"Lines":274,"Code":216,"Comment":0,"Blank":58,"Complexity":0,"Count":2,"WeightedComplexity":0,"Files":[],"LineLength":null,"ULOC":0},{"Name":"Perl","Bytes":9480,"CodeBytes":0,"Lines":273,"Code":260,"Comment":3,"Blank":10,"Complexity":0,"Count":1,"WeightedComplexity":0,"Files":[],"LineLength":null,"ULOC":0},{"Name":"XML","Bytes":327550,"CodeBytes":0,"Lines":12243,"Code":8384,"Comment":7,"Blank":3852,"Complexity":0,"Count":1,"WeightedComplexity":0,"Files":[],"LineLength":null,"ULOC":0}]